codebear/__init__.py
codebear/config.py
codebear/exception.py
codebear-1.0.3.dist-info/LICENSE.txt
codebear-1.0.3.dist-info/METADATA
codebear-1.0.3.dist-info/WHEEL
codebear-1.0.3.dist-info/top_level.txt
codebear-1.0.3.dist-info/RECORD
