Metadata-Version: 2.1
Name: codebear
Version: 1.0.3
Summary: A pygame role package
Home-page: UNKNOWN
Author: yyb
Author-email: 877665814@qq.com
License: MIT
Platform: all
Classifier: Intended Audience :: Developers
Classifier: Operating System :: OS Independent
Classifier: Natural Language :: Chinese (Simplified)
Classifier: Programming Language :: Python
Classifier: Programming Language :: Python :: 3.7
Classifier: Programming Language :: Python :: 3.8
Classifier: Topic :: Software Development :: Libraries
